SpringMvc424ReleaseZhongwenWendang/README.md
SpringMvc424ReleaseZhongwenWendang/__init__.py
SpringMvc424ReleaseZhongwenWendang/__main__.py
SpringMvc424ReleaseZhongwenWendang/file.epub
SpringMvc424ReleaseZhongwenWendang/index.html
SpringMvc424ReleaseZhongwenWendang/css/__init__.py
SpringMvc424ReleaseZhongwenWendang/css/annotations.css
SpringMvc424ReleaseZhongwenWendang/css/main.css
SpringMvc424ReleaseZhongwenWendang/css/normalize.css
SpringMvc424ReleaseZhongwenWendang/css/popup.css
SpringMvc424ReleaseZhongwenWendang/font/__init__.py
SpringMvc424ReleaseZhongwenWendang/font/fontello.eot
SpringMvc424ReleaseZhongwenWendang/font/fontello.svg
SpringMvc424ReleaseZhongwenWendang/font/fontello.ttf
SpringMvc424ReleaseZhongwenWendang/font/fontello.woff
SpringMvc424ReleaseZhongwenWendang/img/__init__.py
SpringMvc424ReleaseZhongwenWendang/img/annotator-glyph-sprite.png
SpringMvc424ReleaseZhongwenWendang/img/annotator-icon-sprite.png
SpringMvc424ReleaseZhongwenWendang/img/apple-touch-icon.png
SpringMvc424ReleaseZhongwenWendang/img/cancelfullscreen.png
SpringMvc424ReleaseZhongwenWendang/img/close.png
SpringMvc424ReleaseZhongwenWendang/img/fullscreen.png
SpringMvc424ReleaseZhongwenWendang/img/loader.gif
SpringMvc424ReleaseZhongwenWendang/img/menu-icon.png
SpringMvc424ReleaseZhongwenWendang/img/save.png
SpringMvc424ReleaseZhongwenWendang/img/saved.png
SpringMvc424ReleaseZhongwenWendang/img/settings-s.png
SpringMvc424ReleaseZhongwenWendang/img/settings.png
SpringMvc424ReleaseZhongwenWendang/img/star.png
SpringMvc424ReleaseZhongwenWendang/js/__init__.py
SpringMvc424ReleaseZhongwenWendang/js/epub.js
SpringMvc424ReleaseZhongwenWendang/js/epub.min.js
SpringMvc424ReleaseZhongwenWendang/js/epub.min.map
SpringMvc424ReleaseZhongwenWendang/js/hooks.min.js
SpringMvc424ReleaseZhongwenWendang/js/hooks.min.map
SpringMvc424ReleaseZhongwenWendang/js/reader.js
SpringMvc424ReleaseZhongwenWendang/js/reader.js.map
SpringMvc424ReleaseZhongwenWendang/js/reader.min.js
spring_mvc_4_2_4_release_zhongwen_wendang-2024.3.2.0.dist-info/METADATA
spring_mvc_4_2_4_release_zhongwen_wendang-2024.3.2.0.dist-info/WHEEL
spring_mvc_4_2_4_release_zhongwen_wendang-2024.3.2.0.dist-info/entry_points.txt
spring_mvc_4_2_4_release_zhongwen_wendang-2024.3.2.0.dist-info/top_level.txt
spring_mvc_4_2_4_release_zhongwen_wendang-2024.3.2.0.dist-info/RECORD
